{
  "project_info": {
    "project_number": "505509689635",
    "firebase_url": "https://myproject-9bf39.firebaseio.com",
    "project_id": "myproject-9bf39",
    "storage_bucket": "myproject-9bf39.appspot.com"
  },
  "client": [
    {
      "client_info": {
        "mobilesdk_app_id": "1:505509689635:android:c3f9ba77b54915f813b496",
        "android_client_info": {
          "package_name": "com.friday.eiy.dry"
        }
      },
      "oauth_client": [
        {
          "client_id": "505509689635-5l3s4c3nl4k36lc6kjknmlbnra19g5j2.apps.googleusercontent.com",
          "client_type": 3
        }
      ],
      "api_key": [
        {
          "current_key": "AIzaSyAMCPlLOi4-cw5k5vX7o81k5vvUc6dEWHk"
        }
      ],
      "services": {
        "appinvite_service": {
          "other_platform_oauth_client": [
            {
              "client_id": "505509689635-5l3s4c3nl4k36lc6kjknmlbnra19g5j2.apps.googleusercontent.com",
              "client_type": 3
            }
          ]
        }
      }
    },
    {
      "client_info": {
        "mobilesdk_app_id": "1:505509689635:android:2b147b0dc0a5493813b496",
        "android_client_info": {
          "package_name": "dev.iey.friday.fbs"
        }
      },
      "oauth_client": [
        {
          "client_id": "505509689635-g0febbflpt1oajn35umr1obktnuagd6s.apps.googleusercontent.com",
          "client_type": 1,
          "android_info": {
            "package_name": "dev.iey.friday.fbs",
            "certificate_hash": "1468b0e4d860b73a3a16601e45fa14e26a9f2933"
          }
        },
        {
          "client_id": "505509689635-5l3s4c3nl4k36lc6kjknmlbnra19g5j2.apps.googleusercontent.com",
          "client_type": 3
        }
      ],
      "api_key": [
        {
          "current_key": "AIzaSyAMCPlLOi4-cw5k5vX7o81k5vvUc6dEWHk"
        }
      ],
      "services": {
        "appinvite_service": {
          "other_platform_oauth_client": [
            {
              "client_id": "505509689635-5l3s4c3nl4k36lc6kjknmlbnra19g5j2.apps.googleusercontent.com",
              "client_type": 3
            }
          ]
        }
      }
    }
  ],
  "configuration_version": "1"
}